fastrq/__init__.py
fastrq/base.py
fastrq/deque.py
fastrq/loader.py
fastrq/priorityqueue.py
fastrq/queue.py
fastrq/stack.py
fastrq-0.2.0.dist-info/LICENSE
fastrq-0.2.0.dist-info/METADATA
fastrq-0.2.0.dist-info/WHEEL
fastrq-0.2.0.dist-info/top_level.txt
fastrq-0.2.0.dist-info/RECORD
