Metadata-Version: 2.1
Name: fastrq
Version: 0.2.0
Summary: Queue, Stack and Priority Queue built on Redis
Home-page: https://github.com/limen/fastrq
Author: LI Mengxiang
Author-email: limengxiang876@gmail.com
Maintainer: LI Mengxiang
Maintainer-email: limengxiang876@gmail.com
License: MIT
Platform: any
Requires-Python: >=2.7, !=3.0.*, !=3.1.*, !=3.2.*, !=3.3.*
Requires-Dist: redis
